firesvm/__init__.py
firesvm/kernels.py
firesvm/svm.py
firesvm/utils.py
FireSVM-0.1.3.dist-info/LICENSE
FireSVM-0.1.3.dist-info/METADATA
FireSVM-0.1.3.dist-info/WHEEL
FireSVM-0.1.3.dist-info/top_level.txt
FireSVM-0.1.3.dist-info/RECORD
