Metadata-Version: 2.1
Name: FireSVM
Version: 0.1.3
Summary: Library containing different variants of the SVM algorithm
Home-page: UNKNOWN
Author: Ayman Lafaz
Author-email: ayman.lafaz@um5r.ac.ma
License: UNKNOWN
Platform: UNKNOWN
